odoo8_addon_pos_order_picking_link-8.0.1.1.0-py2.7-nspkg.pth
odoo_addons/pos_order_picking_link/__openerp__.py
odoo_addons/pos_order_picking_link/__init__.py
odoo_addons/pos_order_picking_link/README.rst
odoo_addons/pos_order_picking_link/models/stock.py
odoo_addons/pos_order_picking_link/models/__init__.py
odoo_addons/pos_order_picking_link/views/stock_view.xml
odoo_addons/pos_order_picking_link/static/description/icon.png
odoo8_addon_pos_order_picking_link-8.0.1.1.0.dist-info/top_level.txt
odoo8_addon_pos_order_picking_link-8.0.1.1.0.dist-info/WHEEL
odoo8_addon_pos_order_picking_link-8.0.1.1.0.dist-info/RECORD
odoo8_addon_pos_order_picking_link-8.0.1.1.0.dist-info/metadata.json
odoo8_addon_pos_order_picking_link-8.0.1.1.0.dist-info/DESCRIPTION.rst
odoo8_addon_pos_order_picking_link-8.0.1.1.0.dist-info/METADATA
odoo8_addon_pos_order_picking_link-8.0.1.1.0.dist-info/namespace_packages.txt
