Metadata-Version: 2.0
Name: odoo8-addon-pos-order-picking-link
Version: 8.0.1.1.0
Summary: Adds link between Pos orders and generated pickings
Home-page: http://www.kmee.com.br
Author: KMEE INFORMATICA LTDA, Odoo Community Association (OCA)
Author-email: support@odoo-community.org
License: AGPL-3
Platform: UNKNOWN
Requires-Dist: odoo (<9.0a,>=8.0a)
Classifier: Programming Language :: Python :: 2.7
Classifier: Framework :: Odoo
Classifier: License :: OSI Approved :: GNU Affero General Public License v3
